sinapy/__init__.py
sinapy-1.4.0.dist-info/METADATA
sinapy-1.4.0.dist-info/WHEEL
sinapy-1.4.0.dist-info/entry_points.txt
sinapy-1.4.0.dist-info/top_level.txt
sinapy-1.4.0.dist-info/RECORD
