Metadata-Version: 2.1
Name: sinapy
Version: 1.4.0
Summary: An asynchronous Python wrapper for the sina API.
Home-page: https://api-free.ir
Author: Mahdi Ahmadi
Author-email: mahdiahmadi.1208@gmail.com
License: MIT
Project-URL: Bug Tracker, https://t.me/dev_jav
Project-URL: Documentation, https://api-free.ir/
Project-URL: Source Code, https://api-free.ir/
Keywords: sina,bot,api,python,asynchronous,aiohttp
Classifier: Development Status :: 5 - Production/Stable
Classifier: Intended Audience :: Developers
Classifier: Topic :: Software Development :: Libraries
Classifier: License :: OSI Approved :: MIT License
Classifier: Programming Language :: Python :: 3
Classifier: Programming Language :: Python :: 3.6
Classifier: Programming Language :: Python :: 3.7
Classifier: Programming Language :: Python :: 3.8
Classifier: Programming Language :: Python :: 3.9
Classifier: Programming Language :: Python :: 3.10
Classifier: Programming Language :: Python :: 3.11
Classifier: Operating System :: OS Independent
Classifier: Operating System :: MacOS
Classifier: Operating System :: Microsoft :: Windows
Classifier: Operating System :: POSIX
Classifier: Environment :: Console
Classifier: Natural Language :: English
Requires-Python: >=3.6
Requires-Dist: aiohttp >=3.8.1
Provides-Extra: dev
Requires-Dist: pytest ; extra == 'dev'
Requires-Dist: black ; extra == 'dev'
Requires-Dist: flake8 ; extra == 'dev'
Provides-Extra: docs
Requires-Dist: mkdocs ; extra == 'docs'
Requires-Dist: pdoc3 ; extra == 'docs'
